ntlm_auth/__init__.py
ntlm_auth/compute_hash.py
ntlm_auth/compute_keys.py
ntlm_auth/compute_response.py
ntlm_auth/constants.py
ntlm_auth/des.py
ntlm_auth/exceptions.py
ntlm_auth/gss_channel_bindings.py
ntlm_auth/messages.py
ntlm_auth/ntlm.py
ntlm_auth/rc4.py
ntlm_auth/session_security.py
ntlm_auth-1.4.0.dist-info/LICENSE
ntlm_auth-1.4.0.dist-info/METADATA
ntlm_auth-1.4.0.dist-info/WHEEL
ntlm_auth-1.4.0.dist-info/top_level.txt
ntlm_auth-1.4.0.dist-info/RECORD
